platforminfo/__init__.py
platforminfo/cli.py
platforminfo/platforminfo.py
platforminfo-1.0.0.dist-info/LICENSE
platforminfo-1.0.0.dist-info/METADATA
platforminfo-1.0.0.dist-info/WHEEL
platforminfo-1.0.0.dist-info/entry_points.txt
platforminfo-1.0.0.dist-info/RECORD
