Metadata-Version: 2.1
Name: platforminfo
Version: 1.0.0
Summary: System info for Python made simple. PlatformInfo is designed to provide a simple, yet granular interface to find system information on all major operating systems within Python.
License: BSD-3-Clause
Author: Tejas Raman
Author-email: tejasraman@icloud.com
Requires-Python: >=3.8,<4.0
Classifier: License :: OSI Approved :: BSD License
Classifier: Programming Language :: Python :: 3
Classifier: Programming Language :: Python :: 3.8
Classifier: Programming Language :: Python :: 3.9
Classifier: Programming Language :: Python :: 3.10
Classifier: Programming Language :: Python :: 3.11
Classifier: Programming Language :: Python :: 3.12
